tool_webp_converter/__init__.py
tool_webp_converter/cli.py
tool_webp_converter/convert.py
tool_webp_converter-0.2.0.dist-info/LICENSE
tool_webp_converter-0.2.0.dist-info/METADATA
tool_webp_converter-0.2.0.dist-info/WHEEL
tool_webp_converter-0.2.0.dist-info/entry_points.txt
tool_webp_converter-0.2.0.dist-info/RECORD
