Metadata-Version: 2.3
Name: tool-webp-converter
Version: 0.2.0
Summary: A tool for optimal WebP image compression
Author: guilhemheinrich
Author-email: guilhem.heinrich@gmail.com
Requires-Python: >=3.10
Classifier: Programming Language :: Python :: 3
Classifier: Programming Language :: Python :: 3.10
Classifier: Programming Language :: Python :: 3.11
Classifier: Programming Language :: Python :: 3.12
Classifier: Programming Language :: Python :: 3.13
Requires-Dist: click (>=8.2.1,<9.0.0)
Requires-Dist: pillow (>=11.3.0,<12.0.0)
